{
  "name": "Taelon Peter",
  "slug": "peterta01",
  "url": "https://www.basketball-reference.com/players/p/peterta01.html",
  "num_tables": 12,
  "tables": [
    {
      "table_id": "last5",
      "csv": "peterta01/last5.csv"
    },
    {
      "table_id": "per_game_stats",
      "csv": "peterta01/per_game_stats.csv"
    },
    {
      "table_id": "stathead_insights",
      "csv": "peterta01/stathead_insights.csv"
    },
    {
      "table_id": "totals_stats",
      "csv": "peterta01/totals_stats.csv"
    },
    {
      "table_id": "per_minute_stats",
      "csv": "peterta01/per_minute_stats.csv"
    },
    {
      "table_id": "advanced",
      "csv": "peterta01/advanced.csv"
    },
    {
      "table_id": "shooting",
      "csv": "peterta01/shooting.csv"
    },
    {
      "table_id": "per_poss",
      "csv": "peterta01/per_poss.csv"
    },
    {
      "table_id": "adj_shooting",
      "csv": "peterta01/adj_shooting.csv"
    },
    {
      "table_id": "pbp_stats",
      "csv": "peterta01/pbp_stats.csv"
    },
    {
      "table_id": "highs-reg-season",
      "csv": "peterta01/highs-reg-season.csv"
    },
    {
      "table_id": "all_college_stats",
      "csv": "peterta01/all_college_stats.csv"
    }
  ]
}